ms3/__init__.py
ms3/_typing.py
ms3/_version.py
ms3/annotations.py
ms3/bs4_measures.py
ms3/bs4_parser.py
ms3/cli.py
ms3/corpus.py
ms3/expand_dcml.py
ms3/ferocious_names.txt
ms3/instrument_defaults.csv
ms3/logger.py
ms3/operations.py
ms3/parse.py
ms3/piece.py
ms3/score.py
ms3/transformations.py
ms3/view.py
ms3/utils/__init__.py
ms3/utils/concat_metadata.py
ms3/utils/constants.py
ms3/utils/frictionless_helpers.py
ms3/utils/functions.py
ms3-2.6.0.dist-info/LICENSE.txt
ms3-2.6.0.dist-info/METADATA
ms3-2.6.0.dist-info/WHEEL
ms3-2.6.0.dist-info/entry_points.txt
ms3-2.6.0.dist-info/top_level.txt
ms3-2.6.0.dist-info/RECORD
