Metadata-Version: 2.2
Name: ms3
Version: 2.6.0
Summary: A parser for MuseScore files, serving as data factory for annotated music corpora.
Home-page: https://github.com/johentsch/ms3
Author: Johannes Hentschel
Author-email: johannes.hentschel@epfl.ch
License: GPL-3.0-only
Project-URL: Documentation, https://ms3.readthedocs.io/
Platform: any
Classifier: Development Status :: 5 - Production/Stable
Classifier: License :: OSI Approved :: GNU General Public License v3 (GPLv3)
Classifier: Natural Language :: English
Classifier: Operating System :: OS Independent
Classifier: Programming Language :: Python :: 3.10
Classifier: Topic :: Multimedia :: Sound/Audio :: Editors
Classifier: Topic :: Scientific/Engineering
Requires-Python: >=3.10
License-File: LICENSE.txt
Requires-Dist: beautifulsoup4
Requires-Dist: frictionless[pandas,visidata]
Requires-Dist: lxml
Requires-Dist: pandas>=1.5.3
Requires-Dist: numpy<2.0.0
Requires-Dist: pathos
Requires-Dist: webcolors
Requires-Dist: tqdm
Requires-Dist: pytablewriter==1.0.0
Requires-Dist: GitPython
Requires-Dist: typing_extensions
Provides-Extra: testing
Requires-Dist: setuptools; extra == "testing"
Requires-Dist: pytest; extra == "testing"
Requires-Dist: pytest-cov; extra == "testing"
Provides-Extra: dev
Requires-Dist: ms3[testing]; extra == "dev"
Requires-Dist: pre-commit; extra == "dev"
Requires-Dist: tox; extra == "dev"
